{
    "page-1.png": [
        {
            "youtube_link": "https://www.youtube.com/watch?v=6XUKtdMRR-M",
            "timing": 0.0
        },
        {
            "youtube_link": "https://www.youtube.com/watch?v=GXjhc8EbY4I",
            "timing": 0.0
        },
        {
            "youtube_link": "https://www.youtube.com/watch?v=-VmQNKaOeEw",
            "timing": 0.0
        },
        {
            "youtube_link": "https://www.youtube.com/watch?v=Ey4n8vqlX_o",
            "timing": 0.0
        },
        {
            "youtube_link": "https://www.youtube.com/watch?v=mwb_OGibysg",
            "timing": 0.0
        },
        {
            "youtube_link": "https://www.youtube.com/watch?v=mAJ9Ifcfqew",
            "timing": 0.0
        }
    ],
    "page-2.png": [
        {
            "youtube_link": "https://www.youtube.com/watch?v=6XUKtdMRR-M",
            "timing": 26.8547885075818
        },
        {
            "youtube_link": "https://www.youtube.com/watch?v=GXjhc8EbY4I",
            "timing": 45.418411811652035
        },
        {
            "youtube_link": "https://www.youtube.com/watch?v=-VmQNKaOeEw",
            "timing": 27.798411811652034
        },
        {
            "youtube_link": "https://www.youtube.com/watch?v=Ey4n8vqlX_o",
            "timing": 67.37841181165203
        },
        {
            "youtube_link": "https://www.youtube.com/watch?v=mwb_OGibysg",
            "timing": 28.098411811652035
        },
        {
            "youtube_link": "https://www.youtube.com/watch?v=mAJ9Ifcfqew",
            "timing": 20.018411811652033
        }
    ],
    "page-3.png": [
        {
            "youtube_link": "https://www.youtube.com/watch?v=6XUKtdMRR-M",
            "timing": 61.11687150837989
        },
        {
            "youtube_link": "https://www.youtube.com/watch?v=GXjhc8EbY4I",
            "timing": 79.51687150837988
        },
        {
            "youtube_link": "https://www.youtube.com/watch?v=-VmQNKaOeEw",
            "timing": 56.32916201117318
        },
        {
            "youtube_link": "https://www.youtube.com/watch?v=Ey4n8vqlX_o",
            "timing": 97.39731843575419
        },
        {
            "youtube_link": "https://www.youtube.com/watch?v=mwb_OGibysg",
            "timing": 55.196871508379886
        },
        {
            "youtube_link": "https://www.youtube.com/watch?v=mAJ9Ifcfqew",
            "timing": 44.876871508379885
        }
    ],
    "page-4.png": [
        {
            "youtube_link": "https://www.youtube.com/watch?v=6XUKtdMRR-M",
            "timing": 93.98007980845968
        },
        {
            "youtube_link": "https://www.youtube.com/watch?v=GXjhc8EbY4I",
            "timing": 114.17011971268951
        },
        {
            "youtube_link": "https://www.youtube.com/watch?v=-VmQNKaOeEw",
            "timing": 85.9950997605746
        },
        {
            "youtube_link": "https://www.youtube.com/watch?v=Ey4n8vqlX_o",
            "timing": 126.97513168395848
        },
        {
            "youtube_link": "https://www.youtube.com/watch?v=mwb_OGibysg",
            "timing": 81.93503591380686
        },
        {
            "youtube_link": "https://www.youtube.com/watch?v=mAJ9Ifcfqew",
            "timing": 69.67511572226653
        }
    ],
    "page-5.png": [
        {
            "youtube_link": "https://www.youtube.com/watch?v=6XUKtdMRR-M",
            "timing": 126.95047086991221
        },
        {
            "youtube_link": "https://www.youtube.com/watch?v=GXjhc8EbY4I",
            "timing": 147.77205905826017
        },
        {
            "youtube_link": "https://www.youtube.com/watch?v=-VmQNKaOeEw",
            "timing": 115.47205905826019
        },
        {
            "youtube_link": "https://www.youtube.com/watch?v=Ey4n8vqlX_o",
            "timing": 156.76888268156424
        },
        {
            "youtube_link": "https://www.youtube.com/watch?v=mwb_OGibysg",
            "timing": 109.07205905826018
        },
        {
            "youtube_link": "https://www.youtube.com/watch?v=mAJ9Ifcfqew",
            "timing": 94.03205905826017
        }
    ],
    "page-6.png": [
        {
            "youtube_link": "https://www.youtube.com/watch?v=6XUKtdMRR-M",
            "timing": 159.9318595371109
        },
        {
            "youtube_link": "https://www.youtube.com/watch?v=GXjhc8EbY4I",
            "timing": 182.5705027932961
        },
        {
            "youtube_link": "https://www.youtube.com/watch?v=-VmQNKaOeEw",
            "timing": 144.8477893056664
        },
        {
            "youtube_link": "https://www.youtube.com/watch?v=Ey4n8vqlX_o",
            "timing": 186.41929768555465
        },
        {
            "youtube_link": "https://www.youtube.com/watch?v=mwb_OGibysg",
            "timing": 134.65050279329608
        },
        {
            "youtube_link": "https://www.youtube.com/watch?v=mAJ9Ifcfqew",
            "timing": 117.67321628092577
        }
    ],
    "page-7.png": [
        {
            "youtube_link": "https://www.youtube.com/watch?v=6XUKtdMRR-M",
            "timing": 189.61458100558653
        },
        {
            "youtube_link": "https://www.youtube.com/watch?v=GXjhc8EbY4I",
            "timing": 214.76462889066238
        },
        {
            "youtube_link": "https://www.youtube.com/watch?v=-VmQNKaOeEw",
            "timing": 174.4046288906624
        },
        {
            "youtube_link": "https://www.youtube.com/watch?v=Ey4n8vqlX_o",
            "timing": 213.7471747805267
        },
        {
            "youtube_link": "https://www.youtube.com/watch?v=mwb_OGibysg",
            "timing": 159.2283320031923
        },
        {
            "youtube_link": "https://www.youtube.com/watch?v=mAJ9Ifcfqew",
            "timing": 139.2871747805267
        }
    ],
    "page-8.png": [
        {
            "youtube_link": "https://www.youtube.com/watch?v=6XUKtdMRR-M",
            "timing": 223.39423782920989
        },
        {
            "youtube_link": "https://www.youtube.com/watch?v=GXjhc8EbY4I",
            "timing": 245.59141260973664
        },
        {
            "youtube_link": "https://www.youtube.com/watch?v=-VmQNKaOeEw",
            "timing": 204.84108539505186
        },
        {
            "youtube_link": "https://www.youtube.com/watch?v=Ey4n8vqlX_o",
            "timing": 241.9914126097366
        },
        {
            "youtube_link": "https://www.youtube.com/watch?v=mwb_OGibysg",
            "timing": 185.0205426975259
        },
        {
            "youtube_link": "https://www.youtube.com/watch?v=mAJ9Ifcfqew",
            "timing": 162.45141260973662
        }
    ],
    "page-9.png": [
        {
            "youtube_link": "https://www.youtube.com/watch?v=6XUKtdMRR-M",
            "timing": 321.12256983240223
        },
        {
            "youtube_link": "https://www.youtube.com/watch?v=GXjhc8EbY4I",
            "timing": 344.11273743016756
        },
        {
            "youtube_link": "https://www.youtube.com/watch?v=-VmQNKaOeEw",
            "timing": 290.87776536312845
        },
        {
            "youtube_link": "https://www.youtube.com/watch?v=Ey4n8vqlX_o",
            "timing": 326.792625698324
        },
        {
            "youtube_link": "https://www.youtube.com/watch?v=mwb_OGibysg",
            "timing": 263.62279329608936
        },
        {
            "youtube_link": "https://www.youtube.com/watch?v=mAJ9Ifcfqew",
            "timing": 229.84256983240223
        }
    ],
    "page-10.png": [
        {
            "youtube_link": "https://www.youtube.com/watch?v=6XUKtdMRR-M",
            "timing": 387.84424581005584
        },
        {
            "youtube_link": "https://www.youtube.com/watch?v=GXjhc8EbY4I",
            "timing": 406.94424581005586
        },
        {
            "youtube_link": "https://www.youtube.com/watch?v=-VmQNKaOeEw",
            "timing": 354.3042458100559
        },
        {
            "youtube_link": "https://www.youtube.com/watch?v=Ey4n8vqlX_o",
            "timing": 381.52424581005585
        },
        {
            "youtube_link": "https://www.youtube.com/watch?v=mwb_OGibysg",
            "timing": 313.00424581005586
        },
        {
            "youtube_link": "https://www.youtube.com/watch?v=mAJ9Ifcfqew",
            "timing": 274.9242458100559
        }
    ],
    "page-11.png": [
        {
            "youtube_link": "https://www.youtube.com/watch?v=6XUKtdMRR-M",
            "timing": 407.4079728651237
        },
        {
            "youtube_link": "https://www.youtube.com/watch?v=GXjhc8EbY4I",
            "timing": 428.8079728651237
        },
        {
            "youtube_link": "https://www.youtube.com/watch?v=-VmQNKaOeEw",
            "timing": 368.6279728651237
        },
        {
            "youtube_link": "https://www.youtube.com/watch?v=Ey4n8vqlX_o",
            "timing": 399.51583240223465
        },
        {
            "youtube_link": "https://www.youtube.com/watch?v=mwb_OGibysg",
            "timing": 336.4597206703911
        },
        {
            "youtube_link": "https://www.youtube.com/watch?v=mAJ9Ifcfqew",
            "timing": 289.43545490822027
        }
    ],
    "page-12.png": [
        {
            "youtube_link": "https://www.youtube.com/watch?v=6XUKtdMRR-M",
            "timing": 414.7344134078212
        },
        {
            "youtube_link": "https://www.youtube.com/watch?v=GXjhc8EbY4I",
            "timing": 436.77648044692734
        },
        {
            "youtube_link": "https://www.youtube.com/watch?v=-VmQNKaOeEw",
            "timing": 375.6544134078212
        },
        {
            "youtube_link": "https://www.youtube.com/watch?v=Ey4n8vqlX_o",
            "timing": 406.89738547486036
        },
        {
            "youtube_link": "https://www.youtube.com/watch?v=mwb_OGibysg",
            "timing": 343.4562011173184
        },
        {
            "youtube_link": "https://www.youtube.com/watch?v=mAJ9Ifcfqew",
            "timing": 296.51692737430164
        }
    ],
    "page-13.png": [
        {
            "youtube_link": "https://www.youtube.com/watch?v=6XUKtdMRR-M",
            "timing": 419.91123703112527
        },
        {
            "youtube_link": "https://www.youtube.com/watch?v=GXjhc8EbY4I",
            "timing": 442.1112370311253
        },
        {
            "youtube_link": "https://www.youtube.com/watch?v=-VmQNKaOeEw",
            "timing": 380.8912370311253
        },
        {
            "youtube_link": "https://www.youtube.com/watch?v=Ey4n8vqlX_o",
            "timing": 412.4912370311253
        },
        {
            "youtube_link": "https://www.youtube.com/watch?v=mwb_OGibysg",
            "timing": 349.4912370311253
        },
        {
            "youtube_link": "https://www.youtube.com/watch?v=mAJ9Ifcfqew",
            "timing": 301.5209896249002
        }
    ],
    "page-14.png": [
        {
            "youtube_link": "https://www.youtube.com/watch?v=6XUKtdMRR-M",
            "timing": 427.6532569832402
        },
        {
            "youtube_link": "https://www.youtube.com/watch?v=GXjhc8EbY4I",
            "timing": 450.16572067039107
        },
        {
            "youtube_link": "https://www.youtube.com/watch?v=-VmQNKaOeEw",
            "timing": 388.6574972067039
        },
        {
            "youtube_link": "https://www.youtube.com/watch?v=Ey4n8vqlX_o",
            "timing": 420.5041340782123
        },
        {
            "youtube_link": "https://www.youtube.com/watch?v=mwb_OGibysg",
            "timing": 357.395687150838
        },
        {
            "youtube_link": "https://www.youtube.com/watch?v=mAJ9Ifcfqew",
            "timing": 308.94033519553074
        }
    ],
    "page-15.png": [
        {
            "youtube_link": "https://www.youtube.com/watch?v=6XUKtdMRR-M",
            "timing": 435.1416600159617
        },
        {
            "youtube_link": "https://www.youtube.com/watch?v=GXjhc8EbY4I",
            "timing": 457.32166001596164
        },
        {
            "youtube_link": "https://www.youtube.com/watch?v=-VmQNKaOeEw",
            "timing": 395.9294333599361
        },
        {
            "youtube_link": "https://www.youtube.com/watch?v=Ey4n8vqlX_o",
            "timing": 428.46943335993615
        },
        {
            "youtube_link": "https://www.youtube.com/watch?v=mwb_OGibysg",
            "timing": 364.90943335993614
        },
        {
            "youtube_link": "https://www.youtube.com/watch?v=mAJ9Ifcfqew",
            "timing": 315.9294333599361
        }
    ],
    "page-16.png": [
        {
            "youtube_link": "https://www.youtube.com/watch?v=6XUKtdMRR-M",
            "timing": 448.7858156424581
        },
        {
            "youtube_link": "https://www.youtube.com/watch?v=GXjhc8EbY4I",
            "timing": 470.34462090981646
        },
        {
            "youtube_link": "https://www.youtube.com/watch?v=-VmQNKaOeEw",
            "timing": 408.582431763767
        },
        {
            "youtube_link": "https://www.youtube.com/watch?v=Ey4n8vqlX_o",
            "timing": 442.4956640063847
        },
        {
            "youtube_link": "https://www.youtube.com/watch?v=mwb_OGibysg",
            "timing": 377.9058156424581
        },
        {
            "youtube_link": "https://www.youtube.com/watch?v=mAJ9Ifcfqew",
            "timing": 327.87464644852355
        }
    ],
    "page-17.png": [
        {
            "youtube_link": "https://www.youtube.com/watch?v=6XUKtdMRR-M",
            "timing": 463.1477094972067
        },
        {
            "youtube_link": "https://www.youtube.com/watch?v=GXjhc8EbY4I",
            "timing": 482.47192019154033
        },
        {
            "youtube_link": "https://www.youtube.com/watch?v=-VmQNKaOeEw",
            "timing": 420.59672785315246
        },
        {
            "youtube_link": "https://www.youtube.com/watch?v=Ey4n8vqlX_o",
            "timing": 456.3857749401436
        },
        {
            "youtube_link": "https://www.youtube.com/watch?v=mwb_OGibysg",
            "timing": 391.3384948124501
        },
        {
            "youtube_link": "https://www.youtube.com/watch?v=mAJ9Ifcfqew",
            "timing": 339.8367278531524
        }
    ],
    "page-18.png": [
        {
            "youtube_link": "https://www.youtube.com/watch?v=6XUKtdMRR-M",
            "timing": 474.4703750997606
        },
        {
            "youtube_link": "https://www.youtube.com/watch?v=GXjhc8EbY4I",
            "timing": 492.90830007980844
        },
        {
            "youtube_link": "https://www.youtube.com/watch?v=-VmQNKaOeEw",
            "timing": 431.32498004788505
        },
        {
            "youtube_link": "https://www.youtube.com/watch?v=Ey4n8vqlX_o",
            "timing": 467.5303750997606
        },
        {
            "youtube_link": "https://www.youtube.com/watch?v=mwb_OGibysg",
            "timing": 403.32103750997607
        },
        {
            "youtube_link": "https://www.youtube.com/watch?v=mAJ9Ifcfqew",
            "timing": 349.8823862729449
        }
    ],
    "page-19.png": [
        {
            "youtube_link": "https://www.youtube.com/watch?v=6XUKtdMRR-M",
            "timing": 486.4982282521947
        },
        {
            "youtube_link": "https://www.youtube.com/watch?v=GXjhc8EbY4I",
            "timing": 505.0085291300878
        },
        {
            "youtube_link": "https://www.youtube.com/watch?v=-VmQNKaOeEw",
            "timing": 443.8712936951317
        },
        {
            "youtube_link": "https://www.youtube.com/watch?v=Ey4n8vqlX_o",
            "timing": 480.6782282521947
        },
        {
            "youtube_link": "https://www.youtube.com/watch?v=mwb_OGibysg",
            "timing": 416.9382282521947
        },
        {
            "youtube_link": "https://www.youtube.com/watch?v=mAJ9Ifcfqew",
            "timing": 362.0365291300878
        }
    ],
    "page-20.png": [
        {
            "youtube_link": "https://www.youtube.com/watch?v=6XUKtdMRR-M",
            "timing": 501.24620111731844
        },
        {
            "youtube_link": "https://www.youtube.com/watch?v=GXjhc8EbY4I",
            "timing": 517.9662114924182
        },
        {
            "youtube_link": "https://www.youtube.com/watch?v=-VmQNKaOeEw",
            "timing": 458.14984996009576
        },
        {
            "youtube_link": "https://www.youtube.com/watch?v=Ey4n8vqlX_o",
            "timing": 495.93864884277735
        },
        {
            "youtube_link": "https://www.youtube.com/watch?v=mwb_OGibysg",
            "timing": 432.4202873104549
        },
        {
            "youtube_link": "https://www.youtube.com/watch?v=mAJ9Ifcfqew",
            "timing": 376.0602873104549
        }
    ],
    "page-21.png": [
        {
            "youtube_link": "https://www.youtube.com/watch?v=6XUKtdMRR-M",
            "timing": 523.1158268156424
        },
        {
            "youtube_link": "https://www.youtube.com/watch?v=GXjhc8EbY4I",
            "timing": 538.0285363128492
        },
        {
            "youtube_link": "https://www.youtube.com/watch?v=-VmQNKaOeEw",
            "timing": 478.97853631284914
        },
        {
            "youtube_link": "https://www.youtube.com/watch?v=Ey4n8vqlX_o",
            "timing": 517.650403830806
        },
        {
            "youtube_link": "https://www.youtube.com/watch?v=mwb_OGibysg",
            "timing": 453.5975019952115
        },
        {
            "youtube_link": "https://www.youtube.com/watch?v=mAJ9Ifcfqew",
            "timing": 394.9994700718276
        }
    ],
    "page-22.png": [
        {
            "youtube_link": "https://www.youtube.com/watch?v=6XUKtdMRR-M",
            "timing": 542.0599840383081
        },
        {
            "youtube_link": "https://www.youtube.com/watch?v=GXjhc8EbY4I",
            "timing": 553.3243998403831
        },
        {
            "youtube_link": "https://www.youtube.com/watch?v=-VmQNKaOeEw",
            "timing": 494.7107996807662
        },
        {
            "youtube_link": "https://www.youtube.com/watch?v=Ey4n8vqlX_o",
            "timing": 537.0199840383082
        },
        {
            "youtube_link": "https://www.youtube.com/watch?v=mwb_OGibysg",
            "timing": 472.6399840383081
        },
        {
            "youtube_link": "https://www.youtube.com/watch?v=mAJ9Ifcfqew",
            "timing": 412.43998403830807
        }
    ],
    "page-23.png": [
        {
            "youtube_link": "https://www.youtube.com/watch?v=6XUKtdMRR-M",
            "timing": 544.641
        },
        {
            "youtube_link": "https://www.youtube.com/watch?v=GXjhc8EbY4I",
            "timing": 553.956744612929
        },
        {
            "youtube_link": "https://www.youtube.com/watch?v=-VmQNKaOeEw",
            "timing": 495.28987230646453
        },
        {
            "youtube_link": "https://www.youtube.com/watch?v=Ey4n8vqlX_o",
            "timing": 539.0029680766162
        },
        {
            "youtube_link": "https://www.youtube.com/watch?v=mwb_OGibysg",
            "timing": 474.921
        },
        {
            "youtube_link": "https://www.youtube.com/watch?v=mAJ9Ifcfqew",
            "timing": 413.6298403830806
        }
    ],
    "page-24.png": [
        {
            "youtube_link": "https://www.youtube.com/watch?v=6XUKtdMRR-M",
            "timing": 546.5895363128492
        },
        {
            "youtube_link": "https://www.youtube.com/watch?v=GXjhc8EbY4I",
            "timing": 555.123
        },
        {
            "youtube_link": "https://www.youtube.com/watch?v=-VmQNKaOeEw",
            "timing": 498.78414525139664
        },
        {
            "youtube_link": "https://www.youtube.com/watch?v=Ey4n8vqlX_o",
            "timing": 543.0336312849162
        },
        {
            "youtube_link": "https://www.youtube.com/watch?v=mwb_OGibysg",
            "timing": 477.25253631284914
        },
        {
            "youtube_link": "https://www.youtube.com/watch?v=mAJ9Ifcfqew",
            "timing": 416.8046815642458
        }
    ],
    "page-25.png": [
        {
            "youtube_link": "https://www.youtube.com/watch?v=6XUKtdMRR-M",
            "timing": 548.9384181963288
        },
        {
            "youtube_link": "https://www.youtube.com/watch?v=GXjhc8EbY4I",
            "timing": 555.134
        },
        {
            "youtube_link": "https://www.youtube.com/watch?v=-VmQNKaOeEw",
            "timing": 502.10867757382283
        },
        {
            "youtube_link": "https://www.youtube.com/watch?v=Ey4n8vqlX_o",
            "timing": 549.0072090981644
        },
        {
            "youtube_link": "https://www.youtube.com/watch?v=mwb_OGibysg",
            "timing": 477.5102090981644
        },
        {
            "youtube_link": "https://www.youtube.com/watch?v=mAJ9Ifcfqew",
            "timing": 419.580522745411
        }
    ],
    "page-26.png": [
        {
            "youtube_link": "https://www.youtube.com/watch?v=6XUKtdMRR-M",
            "timing": 551.6395530726257
        },
        {
            "youtube_link": "https://www.youtube.com/watch?v=GXjhc8EbY4I",
            "timing": 560.5195530726257
        },
        {
            "youtube_link": "https://www.youtube.com/watch?v=-VmQNKaOeEw",
            "timing": 506.18158659217875
        },
        {
            "youtube_link": "https://www.youtube.com/watch?v=Ey4n8vqlX_o",
            "timing": 549.6131955307263
        },
        {
            "youtube_link": "https://www.youtube.com/watch?v=mwb_OGibysg",
            "timing": 482.4033910614525
        },
        {
            "youtube_link": "https://www.youtube.com/watch?v=mAJ9Ifcfqew",
            "timing": 420.3843910614525
        }
    ],
    "page-27.png": [
        {
            "youtube_link": "https://www.youtube.com/watch?v=6XUKtdMRR-M",
            "timing": 557.4379042298484
        },
        {
            "youtube_link": "https://www.youtube.com/watch?v=GXjhc8EbY4I",
            "timing": 565.8078332003192
        },
        {
            "youtube_link": "https://www.youtube.com/watch?v=-VmQNKaOeEw",
            "timing": 510.2340853950519
        },
        {
            "youtube_link": "https://www.youtube.com/watch?v=Ey4n8vqlX_o",
            "timing": 554.0992897047087
        },
        {
            "youtube_link": "https://www.youtube.com/watch?v=mwb_OGibysg",
            "timing": 486.95928970470874
        },
        {
            "youtube_link": "https://www.youtube.com/watch?v=mAJ9Ifcfqew",
            "timing": 424.5263766959298
        }
    ],
    "page-28.png": [
        {
            "youtube_link": "https://www.youtube.com/watch?v=6XUKtdMRR-M",
            "timing": 565.9398324022346
        },
        {
            "youtube_link": "https://www.youtube.com/watch?v=GXjhc8EbY4I",
            "timing": 574.197094972067
        },
        {
            "youtube_link": "https://www.youtube.com/watch?v=-VmQNKaOeEw",
            "timing": 519.0743631284915
        },
        {
            "youtube_link": "https://www.youtube.com/watch?v=Ey4n8vqlX_o",
            "timing": 562.7141899441341
        },
        {
            "youtube_link": "https://www.youtube.com/watch?v=mwb_OGibysg",
            "timing": 496.10547486033516
        },
        {
            "youtube_link": "https://www.youtube.com/watch?v=mAJ9Ifcfqew",
            "timing": 433.42547486033516
        }
    ],
    "page-29.png": [
        {
            "youtube_link": "https://www.youtube.com/watch?v=6XUKtdMRR-M",
            "timing": 575.9362011173184
        },
        {
            "youtube_link": "https://www.youtube.com/watch?v=GXjhc8EbY4I",
            "timing": 583.6754413407821
        },
        {
            "youtube_link": "https://www.youtube.com/watch?v=-VmQNKaOeEw",
            "timing": 530.2371237031125
        },
        {
            "youtube_link": "https://www.youtube.com/watch?v=Ey4n8vqlX_o",
            "timing": 571.7945730247405
        },
        {
            "youtube_link": "https://www.youtube.com/watch?v=mwb_OGibysg",
            "timing": 505.8356584197924
        },
        {
            "youtube_link": "https://www.youtube.com/watch?v=mAJ9Ifcfqew",
            "timing": 443.29565841979246
        }
    ],
    "page-30.png": [
        {
            "youtube_link": "https://www.youtube.com/watch?v=6XUKtdMRR-M",
            "timing": 585.2425698324022
        },
        {
            "youtube_link": "https://www.youtube.com/watch?v=GXjhc8EbY4I",
            "timing": 591.903671189146
        },
        {
            "youtube_link": "https://www.youtube.com/watch?v=-VmQNKaOeEw",
            "timing": 539.3836711891461
        },
        {
            "youtube_link": "https://www.youtube.com/watch?v=Ey4n8vqlX_o",
            "timing": 580.2629369513168
        },
        {
            "youtube_link": "https://www.youtube.com/watch?v=mwb_OGibysg",
            "timing": 514.7236711891461
        },
        {
            "youtube_link": "https://www.youtube.com/watch?v=mAJ9Ifcfqew",
            "timing": 452.92367118914603
        }
    ],
    "page-31.png": [
        {
            "youtube_link": "https://www.youtube.com/watch?v=6XUKtdMRR-M",
            "timing": 606.3785905826016
        },
        {
            "youtube_link": "https://www.youtube.com/watch?v=GXjhc8EbY4I",
            "timing": 612.9867278531524
        },
        {
            "youtube_link": "https://www.youtube.com/watch?v=-VmQNKaOeEw",
            "timing": 559.8389704708699
        },
        {
            "youtube_link": "https://www.youtube.com/watch?v=Ey4n8vqlX_o",
            "timing": 600.70336632083
        },
        {
            "youtube_link": "https://www.youtube.com/watch?v=mwb_OGibysg",
            "timing": 535.1781947326416
        },
        {
            "youtube_link": "https://www.youtube.com/watch?v=mAJ9Ifcfqew",
            "timing": 473.8541237031125
        }
    ],
    "page-32.png": [
        {
            "youtube_link": "https://www.youtube.com/watch?v=6XUKtdMRR-M",
            "timing": 615.2832402234636
        },
        {
            "youtube_link": "https://www.youtube.com/watch?v=GXjhc8EbY4I",
            "timing": 622.2432402234637
        },
        {
            "youtube_link": "https://www.youtube.com/watch?v=-VmQNKaOeEw",
            "timing": 568.5654189944134
        },
        {
            "youtube_link": "https://www.youtube.com/watch?v=Ey4n8vqlX_o",
            "timing": 609.8007653631284
        },
        {
            "youtube_link": "https://www.youtube.com/watch?v=mwb_OGibysg",
            "timing": 544.1886033519553
        },
        {
            "youtube_link": "https://www.youtube.com/watch?v=mAJ9Ifcfqew",
            "timing": 483.2077653631285
        }
    ],
    "page-33.png": [
        {
            "youtube_link": "https://www.youtube.com/watch?v=6XUKtdMRR-M",
            "timing": 634.6814365522745
        },
        {
            "youtube_link": "https://www.youtube.com/watch?v=GXjhc8EbY4I",
            "timing": 640.325790103751
        },
        {
            "youtube_link": "https://www.youtube.com/watch?v=-VmQNKaOeEw",
            "timing": 585.8661436552275
        },
        {
            "youtube_link": "https://www.youtube.com/watch?v=Ey4n8vqlX_o",
            "timing": 627.6850143655226
        },
        {
            "youtube_link": "https://www.youtube.com/watch?v=mwb_OGibysg",
            "timing": 562.6373304070231
        },
        {
            "youtube_link": "https://www.youtube.com/watch?v=mAJ9Ifcfqew",
            "timing": 489.537
        }
    ],
    "page-34.png": [
        {
            "youtube_link": "https://www.youtube.com/watch?v=6XUKtdMRR-M",
            "timing": 645.3905347166799
        },
        {
            "youtube_link": "https://www.youtube.com/watch?v=GXjhc8EbY4I",
            "timing": 650.21053471668
        },
        {
            "youtube_link": "https://www.youtube.com/watch?v=-VmQNKaOeEw",
            "timing": 594.555526735834
        },
        {
            "youtube_link": "https://www.youtube.com/watch?v=Ey4n8vqlX_o",
            "timing": 628.7661053471668
        },
        {
            "youtube_link": "https://www.youtube.com/watch?v=mwb_OGibysg",
            "timing": 571.7761620111731
        },
        {
            "youtube_link": "https://www.youtube.com/watch?v=mAJ9Ifcfqew",
            "timing": 492.03053471667994
        }
    ],
    "page-35.png": [
        {
            "youtube_link": "https://www.youtube.com/watch?v=6XUKtdMRR-M",
            "timing": 659.4293455706305
        },
        {
            "youtube_link": "https://www.youtube.com/watch?v=GXjhc8EbY4I",
            "timing": 663.9845091779729
        },
        {
            "youtube_link": "https://www.youtube.com/watch?v=-VmQNKaOeEw",
            "timing": 608.126025538707
        },
        {
            "youtube_link": "https://www.youtube.com/watch?v=Ey4n8vqlX_o",
            "timing": 628.8142418196329
        },
        {
            "youtube_link": "https://www.youtube.com/watch?v=mwb_OGibysg",
            "timing": 585.3838619313648
        },
        {
            "youtube_link": "https://www.youtube.com/watch?v=mAJ9Ifcfqew",
            "timing": 493.013
        }
    ],
    "page-36.png": [
        {
            "youtube_link": "https://www.youtube.com/watch?v=6XUKtdMRR-M",
            "timing": 666.0210055865921
        },
        {
            "youtube_link": "https://www.youtube.com/watch?v=GXjhc8EbY4I",
            "timing": 670.1967039106145
        },
        {
            "youtube_link": "https://www.youtube.com/watch?v=-VmQNKaOeEw",
            "timing": 614.1672737430167
        },
        {
            "youtube_link": "https://www.youtube.com/watch?v=Ey4n8vqlX_o",
            "timing": 629.0348100558659
        },
        {
            "youtube_link": "https://www.youtube.com/watch?v=mwb_OGibysg",
            "timing": 592.2224022346369
        },
        {
            "youtube_link": "https://www.youtube.com/watch?v=mAJ9Ifcfqew",
            "timing": 493.54462011173183
        }
    ],
    "page-37.png": [
        {
            "youtube_link": "https://www.youtube.com/watch?v=6XUKtdMRR-M",
            "timing": 672.8026975259378
        },
        {
            "youtube_link": "https://www.youtube.com/watch?v=GXjhc8EbY4I",
            "timing": 676.7136185155626
        },
        {
            "youtube_link": "https://www.youtube.com/watch?v=-VmQNKaOeEw",
            "timing": 620.9740462889066
        },
        {
            "youtube_link": "https://www.youtube.com/watch?v=Ey4n8vqlX_o",
            "timing": 629.1753782920989
        },
        {
            "youtube_link": "https://www.youtube.com/watch?v=mwb_OGibysg",
            "timing": 599.100806065443
        },
        {
            "youtube_link": "https://www.youtube.com/watch?v=mAJ9Ifcfqew",
            "timing": 495.5852697525938
        }
    ],
    "page-38.png": [
        {
            "youtube_link": "https://www.youtube.com/watch?v=6XUKtdMRR-M",
            "timing": 681.3383958499601
        },
        {
            "youtube_link": "https://www.youtube.com/watch?v=GXjhc8EbY4I",
            "timing": 684.0981284916201
        },
        {
            "youtube_link": "https://www.youtube.com/watch?v=-VmQNKaOeEw",
            "timing": 630.2375937749401
        },
        {
            "youtube_link": "https://www.youtube.com/watch?v=Ey4n8vqlX_o",
            "timing": 629.5019465283319
        },
        {
            "youtube_link": "https://www.youtube.com/watch?v=mwb_OGibysg",
            "timing": 606.8181284916201
        },
        {
            "youtube_link": "https://www.youtube.com/watch?v=mAJ9Ifcfqew",
            "timing": 497.522946528332
        }
    ],
    "page-39.png": [
        {
            "youtube_link": "https://www.youtube.com/watch?v=6XUKtdMRR-M",
            "timing": 688.3972146847566
        },
        {
            "youtube_link": "https://www.youtube.com/watch?v=GXjhc8EbY4I",
            "timing": 690.6463288108539
        },
        {
            "youtube_link": "https://www.youtube.com/watch?v=-VmQNKaOeEw",
            "timing": 636.9220670391061
        },
        {
            "youtube_link": "https://www.youtube.com/watch?v=Ey4n8vqlX_o",
            "timing": 630.0771221069433
        },
        {
            "youtube_link": "https://www.youtube.com/watch?v=mwb_OGibysg",
            "timing": 613.4863288108539
        },
        {
            "youtube_link": "https://www.youtube.com/watch?v=mAJ9Ifcfqew",
            "timing": 498.3160295291301
        }
    ],
    "page-40.png": [
        {
            "youtube_link": "https://www.youtube.com/watch?v=6XUKtdMRR-M",
            "timing": 696.0574700718275
        },
        {
            "youtube_link": "https://www.youtube.com/watch?v=GXjhc8EbY4I",
            "timing": 697.9985610534717
        },
        {
            "youtube_link": "https://www.youtube.com/watch?v=-VmQNKaOeEw",
            "timing": 644.1883000798084
        },
        {
            "youtube_link": "https://www.youtube.com/watch?v=Ey4n8vqlX_o",
            "timing": 630.7708300079809
        },
        {
            "youtube_link": "https://www.youtube.com/watch?v=mwb_OGibysg",
            "timing": 620.6033200319234
        },
        {
            "youtube_link": "https://www.youtube.com/watch?v=mAJ9Ifcfqew",
            "timing": 499.3010830007981
        }
    ],
    "page-41.png": [
        {
            "youtube_link": "https://www.youtube.com/watch?v=6XUKtdMRR-M",
            "timing": 702.7843056664007
        },
        {
            "youtube_link": "https://www.youtube.com/watch?v=GXjhc8EbY4I",
            "timing": 704.8643056664007
        },
        {
            "youtube_link": "https://www.youtube.com/watch?v=-VmQNKaOeEw",
            "timing": 650.7425618515563
        },
        {
            "youtube_link": "https://www.youtube.com/watch?v=Ey4n8vqlX_o",
            "timing": 631.563
        },
        {
            "youtube_link": "https://www.youtube.com/watch?v=mwb_OGibysg",
            "timing": 627.3643056664007
        },
        {
            "youtube_link": "https://www.youtube.com/watch?v=mAJ9Ifcfqew",
            "timing": 501.6736512370311
        }
    ],
    "page-42.png": [
        {
            "youtube_link": "https://www.youtube.com/watch?v=6XUKtdMRR-M",
            "timing": 716.9727765363128
        },
        {
            "youtube_link": "https://www.youtube.com/watch?v=GXjhc8EbY4I",
            "timing": 719.6587709497206
        },
        {
            "youtube_link": "https://www.youtube.com/watch?v=-VmQNKaOeEw",
            "timing": 664.2593854748603
        },
        {
            "youtube_link": "https://www.youtube.com/watch?v=Ey4n8vqlX_o",
            "timing": 632.317
        },
        {
            "youtube_link": "https://www.youtube.com/watch?v=mwb_OGibysg",
            "timing": 641.0451396648044
        },
        {
            "youtube_link": "https://www.youtube.com/watch?v=mAJ9Ifcfqew",
            "timing": 503.313
        }
    ],
    "page-43.png": [
        {
            "youtube_link": "https://www.youtube.com/watch?v=6XUKtdMRR-M",
            "timing": 727.3078691141262
        },
        {
            "youtube_link": "https://www.youtube.com/watch?v=GXjhc8EbY4I",
            "timing": 729.0878691141262
        },
        {
            "youtube_link": "https://www.youtube.com/watch?v=-VmQNKaOeEw",
            "timing": 672.9102952913009
        },
        {
            "youtube_link": "https://www.youtube.com/watch?v=Ey4n8vqlX_o",
            "timing": 633.378
        },
        {
            "youtube_link": "https://www.youtube.com/watch?v=mwb_OGibysg",
            "timing": 650.5278691141261
        },
        {
            "youtube_link": "https://www.youtube.com/watch?v=mAJ9Ifcfqew",
            "timing": 503.59
        }
    ],
    "page-44.png": [
        {
            "youtube_link": "https://www.youtube.com/watch?v=6XUKtdMRR-M",
            "timing": 741.3215163607342
        },
        {
            "youtube_link": "https://www.youtube.com/watch?v=GXjhc8EbY4I",
            "timing": 742.4615163607342
        },
        {
            "youtube_link": "https://www.youtube.com/watch?v=-VmQNKaOeEw",
            "timing": 685.6346975259378
        },
        {
            "youtube_link": "https://www.youtube.com/watch?v=Ey4n8vqlX_o",
            "timing": 635.7951516360733
        },
        {
            "youtube_link": "https://www.youtube.com/watch?v=mwb_OGibysg",
            "timing": 664.2112274541101
        },
        {
            "youtube_link": "https://www.youtube.com/watch?v=mAJ9Ifcfqew",
            "timing": 504.4260303272147
        }
    ],
    "page-45.png": [
        {
            "youtube_link": "https://www.youtube.com/watch?v=6XUKtdMRR-M",
            "timing": 763.6573942537908
        },
        {
            "youtube_link": "https://www.youtube.com/watch?v=GXjhc8EbY4I",
            "timing": 764.7703910614524
        },
        {
            "youtube_link": "https://www.youtube.com/watch?v=-VmQNKaOeEw",
            "timing": 705.8575897845171
        },
        {
            "youtube_link": "https://www.youtube.com/watch?v=Ey4n8vqlX_o",
            "timing": 651.6119872306464
        },
        {
            "youtube_link": "https://www.youtube.com/watch?v=mwb_OGibysg",
            "timing": 685.2226288906623
        },
        {
            "youtube_link": "https://www.youtube.com/watch?v=mAJ9Ifcfqew",
            "timing": 525.3723519553072
        }
    ],
    "page-46.png": [
        {
            "youtube_link": "https://www.youtube.com/watch?v=6XUKtdMRR-M",
            "timing": 771.0545730247406
        },
        {
            "youtube_link": "https://www.youtube.com/watch?v=GXjhc8EbY4I",
            "timing": 771.8918595371109
        },
        {
            "youtube_link": "https://www.youtube.com/watch?v=-VmQNKaOeEw",
            "timing": 713.3145730247406
        },
        {
            "youtube_link": "https://www.youtube.com/watch?v=Ey4n8vqlX_o",
            "timing": 659.1088108539506
        },
        {
            "youtube_link": "https://www.youtube.com/watch?v=mwb_OGibysg",
            "timing": 692.7288108539506
        },
        {
            "youtube_link": "https://www.youtube.com/watch?v=mAJ9Ifcfqew",
            "timing": 532.2530486831604
        }
    ],
    "page-47.png": [
        {
            "youtube_link": "https://www.youtube.com/watch?v=6XUKtdMRR-M",
            "timing": 779.2982314445331
        },
        {
            "youtube_link": "https://www.youtube.com/watch?v=GXjhc8EbY4I",
            "timing": 779.8913806863527
        },
        {
            "youtube_link": "https://www.youtube.com/watch?v=-VmQNKaOeEw",
            "timing": 721.5485075818036
        },
        {
            "youtube_link": "https://www.youtube.com/watch?v=Ey4n8vqlX_o",
            "timing": 666.5670710295292
        },
        {
            "youtube_link": "https://www.youtube.com/watch?v=mwb_OGibysg",
            "timing": 699.8945019952115
        },
        {
            "youtube_link": "https://www.youtube.com/watch?v=mAJ9Ifcfqew",
            "timing": 539.9456344772547
        }
    ],
    "page-48.png": [
        {
            "youtube_link": "https://www.youtube.com/watch?v=6XUKtdMRR-M",
            "timing": 789.93473264166
        },
        {
            "youtube_link": "https://www.youtube.com/watch?v=GXjhc8EbY4I",
            "timing": 790.33473264166
        },
        {
            "youtube_link": "https://www.youtube.com/watch?v=-VmQNKaOeEw",
            "timing": 731.955259377494
        },
        {
            "youtube_link": "https://www.youtube.com/watch?v=Ey4n8vqlX_o",
            "timing": 676.73473264166
        },
        {
            "youtube_link": "https://www.youtube.com/watch?v=mwb_OGibysg",
            "timing": 709.357893056664
        },
        {
            "youtube_link": "https://www.youtube.com/watch?v=mAJ9Ifcfqew",
            "timing": 550.11473264166
        }
    ],
    "page-49.png": [
        {
            "youtube_link": "https://www.youtube.com/watch?v=6XUKtdMRR-M",
            "timing": 797.2423423782922
        },
        {
            "youtube_link": "https://www.youtube.com/watch?v=GXjhc8EbY4I",
            "timing": 797.0075426975259
        },
        {
            "youtube_link": "https://www.youtube.com/watch?v=-VmQNKaOeEw",
            "timing": 738.7315562649641
        },
        {
            "youtube_link": "https://www.youtube.com/watch?v=Ey4n8vqlX_o",
            "timing": 684.1075426975259
        },
        {
            "youtube_link": "https://www.youtube.com/watch?v=mwb_OGibysg",
            "timing": 716.3315562649641
        },
        {
            "youtube_link": "https://www.youtube.com/watch?v=mAJ9Ifcfqew",
            "timing": 557.1715562649641
        }
    ],
    "page-50.png": [
        {
            "youtube_link": "https://www.youtube.com/watch?v=6XUKtdMRR-M",
            "timing": 804.7083798882683
        },
        {
            "youtube_link": "https://www.youtube.com/watch?v=GXjhc8EbY4I",
            "timing": 805.3883798882682
        },
        {
            "youtube_link": "https://www.youtube.com/watch?v=-VmQNKaOeEw",
            "timing": 746.9683798882683
        },
        {
            "youtube_link": "https://www.youtube.com/watch?v=Ey4n8vqlX_o",
            "timing": 691.7969385474861
        },
        {
            "youtube_link": "https://www.youtube.com/watch?v=mwb_OGibysg",
            "timing": 724.0883798882683
        },
        {
            "youtube_link": "https://www.youtube.com/watch?v=mAJ9Ifcfqew",
            "timing": 564.9483798882683
        }
    ],
    "page-51.png": [
        {
            "youtube_link": "https://www.youtube.com/watch?v=6XUKtdMRR-M",
            "timing": 824.5543016759776
        },
        {
            "youtube_link": "https://www.youtube.com/watch?v=GXjhc8EbY4I",
            "timing": 825.8743016759776
        },
        {
            "youtube_link": "https://www.youtube.com/watch?v=-VmQNKaOeEw",
            "timing": 765.8743016759776
        },
        {
            "youtube_link": "https://www.youtube.com/watch?v=Ey4n8vqlX_o",
            "timing": 710.9543016759776
        },
        {
            "youtube_link": "https://www.youtube.com/watch?v=mwb_OGibysg",
            "timing": 742.9143016759776
        },
        {
            "youtube_link": "https://www.youtube.com/watch?v=mAJ9Ifcfqew",
            "timing": 584.7743016759775
        }
    ],
    "page-52.png": [
        {
            "youtube_link": "https://www.youtube.com/watch?v=6XUKtdMRR-M",
            "timing": 831.2911252992817
        },
        {
            "youtube_link": "https://www.youtube.com/watch?v=GXjhc8EbY4I",
            "timing": 832.0711252992817
        },
        {
            "youtube_link": "https://www.youtube.com/watch?v=-VmQNKaOeEw",
            "timing": 772.5224900239425
        },
        {
            "youtube_link": "https://www.youtube.com/watch?v=Ey4n8vqlX_o",
            "timing": 718.6511252992817
        },
        {
            "youtube_link": "https://www.youtube.com/watch?v=mwb_OGibysg",
            "timing": 749.6911252992817
        },
        {
            "youtube_link": "https://www.youtube.com/watch?v=mAJ9Ifcfqew",
            "timing": 591.8311252992817
        }
    ],
    "page-53.png": [
        {
            "youtube_link": "https://www.youtube.com/watch?v=6XUKtdMRR-M",
            "timing": 837.7903591380685
        },
        {
            "youtube_link": "https://www.youtube.com/watch?v=GXjhc8EbY4I",
            "timing": 838.2279489225857
        },
        {
            "youtube_link": "https://www.youtube.com/watch?v=-VmQNKaOeEw",
            "timing": 779.0479489225856
        },
        {
            "youtube_link": "https://www.youtube.com/watch?v=Ey4n8vqlX_o",
            "timing": 725.443094972067
        },
        {
            "youtube_link": "https://www.youtube.com/watch?v=mwb_OGibysg",
            "timing": 756.3879489225857
        },
        {
            "youtube_link": "https://www.youtube.com/watch?v=mAJ9Ifcfqew",
            "timing": 598.5079489225857
        }
    ],
    "page-54.png": [
        {
            "youtube_link": "https://www.youtube.com/watch?v=6XUKtdMRR-M",
            "timing": 857.1166320830008
        },
        {
            "youtube_link": "https://www.youtube.com/watch?v=GXjhc8EbY4I",
            "timing": 856.2538707102952
        },
        {
            "youtube_link": "https://www.youtube.com/watch?v=-VmQNKaOeEw",
            "timing": 799.2738707102953
        },
        {
            "youtube_link": "https://www.youtube.com/watch?v=Ey4n8vqlX_o",
            "timing": 742.1750837988826
        },
        {
            "youtube_link": "https://www.youtube.com/watch?v=mwb_OGibysg",
            "timing": 773.4738707102953
        },
        {
            "youtube_link": "https://www.youtube.com/watch?v=mAJ9Ifcfqew",
            "timing": 617.0945450917798
        }
    ],
    "page-55.png": [
        {
            "youtube_link": "https://www.youtube.com/watch?v=6XUKtdMRR-M",
            "timing": 868.9337190742218
        },
        {
            "youtube_link": "https://www.youtube.com/watch?v=GXjhc8EbY4I",
            "timing": 867.922865123703
        },
        {
            "youtube_link": "https://www.youtube.com/watch?v=-VmQNKaOeEw",
            "timing": 810.6913407821228
        },
        {
            "youtube_link": "https://www.youtube.com/watch?v=Ey4n8vqlX_o",
            "timing": 753.7028651237031
        },
        {
            "youtube_link": "https://www.youtube.com/watch?v=mwb_OGibysg",
            "timing": 785.0828651237031
        },
        {
            "youtube_link": "https://www.youtube.com/watch?v=mAJ9Ifcfqew",
            "timing": 628.282865123703
        }
    ],
    "page-56.png": [
        {
            "youtube_link": "https://www.youtube.com/watch?v=6XUKtdMRR-M",
            "timing": 877.8234604948125
        },
        {
            "youtube_link": "https://www.youtube.com/watch?v=GXjhc8EbY4I",
            "timing": 877.9156903431764
        },
        {
            "youtube_link": "https://www.youtube.com/watch?v=-VmQNKaOeEw",
            "timing": 819.6070391061453
        },
        {
            "youtube_link": "https://www.youtube.com/watch?v=Ey4n8vqlX_o",
            "timing": 762.4421707901038
        },
        {
            "youtube_link": "https://www.youtube.com/watch?v=mwb_OGibysg",
            "timing": 794.2121707901038
        },
        {
            "youtube_link": "https://www.youtube.com/watch?v=mAJ9Ifcfqew",
            "timing": 638.6485522745411
        }
    ],
    "page-57.png": [
        {
            "youtube_link": "https://www.youtube.com/watch?v=6XUKtdMRR-M",
            "timing": 893.8728922585794
        },
        {
            "youtube_link": "https://www.youtube.com/watch?v=GXjhc8EbY4I",
            "timing": 894.0501237031126
        },
        {
            "youtube_link": "https://www.youtube.com/watch?v=-VmQNKaOeEw",
            "timing": 833.530263367917
        },
        {
            "youtube_link": "https://www.youtube.com/watch?v=Ey4n8vqlX_o",
            "timing": 777.870263367917
        },
        {
            "youtube_link": "https://www.youtube.com/watch?v=mwb_OGibysg",
            "timing": 808.910263367917
        },
        {
            "youtube_link": "https://www.youtube.com/watch?v=mAJ9Ifcfqew",
            "timing": 653.690263367917
        }
    ],
    "page-58.png": [
        {
            "youtube_link": "https://www.youtube.com/watch?v=6XUKtdMRR-M",
            "timing": 901.0082378292099
        },
        {
            "youtube_link": "https://www.youtube.com/watch?v=GXjhc8EbY4I",
            "timing": 900.7588347964884
        },
        {
            "youtube_link": "https://www.youtube.com/watch?v=-VmQNKaOeEw",
            "timing": 839.887086991221
        },
        {
            "youtube_link": "https://www.youtube.com/watch?v=Ey4n8vqlX_o",
            "timing": 784.807086991221
        },
        {
            "youtube_link": "https://www.youtube.com/watch?v=mwb_OGibysg",
            "timing": 815.8082521947326
        },
        {
            "youtube_link": "https://www.youtube.com/watch?v=mAJ9Ifcfqew",
            "timing": 660.7129608938546
        }
    ],
    "page-59.png": [
        {
            "youtube_link": "https://www.youtube.com/watch?v=6XUKtdMRR-M",
            "timing": 908.7039106145252
        },
        {
            "youtube_link": "https://www.youtube.com/watch?v=GXjhc8EbY4I",
            "timing": 908.2439106145251
        },
        {
            "youtube_link": "https://www.youtube.com/watch?v=-VmQNKaOeEw",
            "timing": 846.4839106145251
        },
        {
            "youtube_link": "https://www.youtube.com/watch?v=Ey4n8vqlX_o",
            "timing": 792.2639106145251
        },
        {
            "youtube_link": "https://www.youtube.com/watch?v=mwb_OGibysg",
            "timing": 822.9012122905027
        },
        {
            "youtube_link": "https://www.youtube.com/watch?v=mAJ9Ifcfqew",
            "timing": 668.0239106145251
        }
    ],
    "page-60.png": [
        {
            "youtube_link": "https://www.youtube.com/watch?v=6XUKtdMRR-M",
            "timing": 914.2342298483638
        },
        {
            "youtube_link": "https://www.youtube.com/watch?v=GXjhc8EbY4I",
            "timing": 913.3925379090183
        },
        {
            "youtube_link": "https://www.youtube.com/watch?v=-VmQNKaOeEw",
            "timing": 851.3690151636074
        },
        {
            "youtube_link": "https://www.youtube.com/watch?v=Ey4n8vqlX_o",
            "timing": 797.4942298483638
        },
        {
            "youtube_link": "https://www.youtube.com/watch?v=mwb_OGibysg",
            "timing": 827.173592178771
        },
        {
            "youtube_link": "https://www.youtube.com/watch?v=mAJ9Ifcfqew",
            "timing": 672.9742298483638
        }
    ],
    "page-61.png": [
        {
            "youtube_link": "https://www.youtube.com/watch?v=6XUKtdMRR-M",
            "timing": 918.8595131683958
        },
        {
            "youtube_link": "https://www.youtube.com/watch?v=GXjhc8EbY4I",
            "timing": 918.4743096568236
        },
        {
            "youtube_link": "https://www.youtube.com/watch?v=-VmQNKaOeEw",
            "timing": 855.7988627294492
        },
        {
            "youtube_link": "https://www.youtube.com/watch?v=Ey4n8vqlX_o",
            "timing": 802.3943096568236
        },
        {
            "youtube_link": "https://www.youtube.com/watch?v=mwb_OGibysg",
            "timing": 831.8151875498802
        },
        {
            "youtube_link": "https://www.youtube.com/watch?v=mAJ9Ifcfqew",
            "timing": 678.1995131683957
        }
    ],
    "page-62.png": [
        {
            "youtube_link": "https://www.youtube.com/watch?v=6XUKtdMRR-M",
            "timing": 925.4498324022346
        },
        {
            "youtube_link": "https://www.youtube.com/watch?v=GXjhc8EbY4I",
            "timing": 924.7684078212291
        },
        {
            "youtube_link": "https://www.youtube.com/watch?v=-VmQNKaOeEw",
            "timing": 861.8498044692736
        },
        {
            "youtube_link": "https://www.youtube.com/watch?v=Ey4n8vqlX_o",
            "timing": 808.9834078212291
        },
        {
            "youtube_link": "https://www.youtube.com/watch?v=mwb_OGibysg",
            "timing": 838.314217877095
        },
        {
            "youtube_link": "https://www.youtube.com/watch?v=mAJ9Ifcfqew",
            "timing": 684.6209497206704
        }
    ],
    "page-63.png": [
        {
            "youtube_link": "https://www.youtube.com/watch?v=6XUKtdMRR-M",
            "timing": 942.4266560255387
        },
        {
            "youtube_link": "https://www.youtube.com/watch?v=GXjhc8EbY4I",
            "timing": 939.9266560255387
        },
        {
            "youtube_link": "https://www.youtube.com/watch?v=-VmQNKaOeEw",
            "timing": 876.3866560255387
        },
        {
            "youtube_link": "https://www.youtube.com/watch?v=Ey4n8vqlX_o",
            "timing": 820.0066560255387
        },
        {
            "youtube_link": "https://www.youtube.com/watch?v=mwb_OGibysg",
            "timing": 847.8466560255388
        },
        {
            "youtube_link": "https://www.youtube.com/watch?v=mAJ9Ifcfqew",
            "timing": 696.4266560255387
        }
    ],
    "page-64.png": [
        {
            "youtube_link": "https://www.youtube.com/watch?v=6XUKtdMRR-M",
            "timing": 952.7086033519553
        },
        {
            "youtube_link": "https://www.youtube.com/watch?v=GXjhc8EbY4I",
            "timing": 951.2357541899441
        },
        {
            "youtube_link": "https://www.youtube.com/watch?v=-VmQNKaOeEw",
            "timing": 889.5557541899441
        },
        {
            "youtube_link": "https://www.youtube.com/watch?v=Ey4n8vqlX_o",
            "timing": 831.5446648044692
        },
        {
            "youtube_link": "https://www.youtube.com/watch?v=mwb_OGibysg",
            "timing": 857.0921787709497
        },
        {
            "youtube_link": "https://www.youtube.com/watch?v=mAJ9Ifcfqew",
            "timing": 707.0757541899441
        }
    ],
    "page-65.png": [
        {
            "youtube_link": "https://www.youtube.com/watch?v=6XUKtdMRR-M",
            "timing": 958.4364405426975
        },
        {
            "youtube_link": "https://www.youtube.com/watch?v=GXjhc8EbY4I",
            "timing": 957.353152434158
        },
        {
            "youtube_link": "https://www.youtube.com/watch?v=-VmQNKaOeEw",
            "timing": 895.5964405426976
        },
        {
            "youtube_link": "https://www.youtube.com/watch?v=Ey4n8vqlX_o",
            "timing": 837.6564405426975
        },
        {
            "youtube_link": "https://www.youtube.com/watch?v=mwb_OGibysg",
            "timing": 862.6164405426975
        },
        {
            "youtube_link": "https://www.youtube.com/watch?v=mAJ9Ifcfqew",
            "timing": 712.7364405426976
        }
    ],
    "page-66.png": [
        {
            "youtube_link": "https://www.youtube.com/watch?v=6XUKtdMRR-M",
            "timing": 964.8786113328013
        },
        {
            "youtube_link": "https://www.youtube.com/watch?v=GXjhc8EbY4I",
            "timing": 963.6893056664006
        },
        {
            "youtube_link": "https://www.youtube.com/watch?v=-VmQNKaOeEw",
            "timing": 902.8332641660016
        },
        {
            "youtube_link": "https://www.youtube.com/watch?v=Ey4n8vqlX_o",
            "timing": 844.8463750997606
        },
        {
            "youtube_link": "https://www.youtube.com/watch?v=mwb_OGibysg",
            "timing": 869.5310175578611
        },
        {
            "youtube_link": "https://www.youtube.com/watch?v=mAJ9Ifcfqew",
            "timing": 720.0986113328013
        }
    ],
    "page-67.png": [
        {
            "youtube_link": "https://www.youtube.com/watch?v=6XUKtdMRR-M",
            "timing": 981.9488427773344
        },
        {
            "youtube_link": "https://www.youtube.com/watch?v=GXjhc8EbY4I",
            "timing": 978.9888427773345
        },
        {
            "youtube_link": "https://www.youtube.com/watch?v=-VmQNKaOeEw",
            "timing": 923.6488427773345
        },
        {
            "youtube_link": "https://www.youtube.com/watch?v=Ey4n8vqlX_o",
            "timing": 858.1829561053472
        },
        {
            "youtube_link": "https://www.youtube.com/watch?v=mwb_OGibysg",
            "timing": 883.2888427773345
        },
        {
            "youtube_link": "https://www.youtube.com/watch?v=mAJ9Ifcfqew",
            "timing": 736.1288427773345
        }
    ],
    "page-68.png": [
        {
            "youtube_link": "https://www.youtube.com/watch?v=6XUKtdMRR-M",
            "timing": 1004.2211173184356
        },
        {
            "youtube_link": "https://www.youtube.com/watch?v=GXjhc8EbY4I",
            "timing": 996.6979409417397
        },
        {
            "youtube_link": "https://www.youtube.com/watch?v=-VmQNKaOeEw",
            "timing": 944.5979409417397
        },
        {
            "youtube_link": "https://www.youtube.com/watch?v=Ey4n8vqlX_o",
            "timing": 870.1347645650438
        },
        {
            "youtube_link": "https://www.youtube.com/watch?v=mwb_OGibysg",
            "timing": 895.4173822825219
        },
        {
            "youtube_link": "https://www.youtube.com/watch?v=mAJ9Ifcfqew",
            "timing": 755.9547645650438
        }
    ],
    "page-69.png": [
        {
            "youtube_link": "https://www.youtube.com/watch?v=6XUKtdMRR-M",
            "timing": 1016.9193136472466
        },
        {
            "youtube_link": "https://www.youtube.com/watch?v=GXjhc8EbY4I",
            "timing": 1008.3393136472466
        },
        {
            "youtube_link": "https://www.youtube.com/watch?v=-VmQNKaOeEw",
            "timing": 957.0993136472466
        },
        {
            "youtube_link": "https://www.youtube.com/watch?v=Ey4n8vqlX_o",
            "timing": 883.0793136472465
        },
        {
            "youtube_link": "https://www.youtube.com/watch?v=mwb_OGibysg",
            "timing": 906.7993136472465
        },
        {
            "youtube_link": "https://www.youtube.com/watch?v=mAJ9Ifcfqew",
            "timing": 768.0393136472466
        }
    ]
}