{
  "staff_0.png": [
    {
      "youtube_link": "https://www.youtube.com/watch?v=-QxRTIQ1sR8",
      "timing": 0.4
    },
    {
      "youtube_link": "https://www.youtube.com/watch?v=5ZxEn-dsvw8",
      "timing": 0.4
    },
    {
      "youtube_link": "https://www.youtube.com/watch?v=aBfdruMBBz8",
      "timing": 0.42
    },
    {
      "youtube_link": "https://www.youtube.com/watch?v=MWTW7Jj1RcU",
      "timing": 0.4
    },
    {
      "youtube_link": "https://www.youtube.com/watch?v=MZ-53dpPPr0",
      "timing": 0.4
    },
    {
      "youtube_link": "https://www.youtube.com/watch?v=OfrxgQQqaA8",
      "timing": 0.4
    },
    {
      "youtube_link": "https://www.youtube.com/watch?v=R5EoRegSyDw",
      "timing": 0.42
    },
    {
      "youtube_link": "https://www.youtube.com/watch?v=rLvve9ks3Xs",
      "timing": 0.4
    },
    {
      "youtube_link": "https://www.youtube.com/watch?v=sfkXHfz6AtE",
      "timing": 0.4
    },
    {
      "youtube_link": "https://www.youtube.com/watch?v=wacmaxGoaO0",
      "timing": 0.28
    }
  ],
  "staff_1.png": [
    {
      "youtube_link": "https://www.youtube.com/watch?v=-QxRTIQ1sR8",
      "timing": 2.0873
    },
    {
      "youtube_link": "https://www.youtube.com/watch?v=5ZxEn-dsvw8",
      "timing": 3.0352
    },
    {
      "youtube_link": "https://www.youtube.com/watch?v=aBfdruMBBz8",
      "timing": 4.0733
    },
    {
      "youtube_link": "https://www.youtube.com/watch?v=MWTW7Jj1RcU",
      "timing": 4.06
    },
    {
      "youtube_link": "https://www.youtube.com/watch?v=MZ-53dpPPr0",
      "timing": 5.24
    },
    {
      "youtube_link": "https://www.youtube.com/watch?v=OfrxgQQqaA8",
      "timing": 5.5
    },
    {
      "youtube_link": "https://www.youtube.com/watch?v=R5EoRegSyDw",
      "timing": 6.02
    },
    {
      "youtube_link": "https://www.youtube.com/watch?v=rLvve9ks3Xs",
      "timing": 3.724
    },
    {
      "youtube_link": "https://www.youtube.com/watch?v=sfkXHfz6AtE",
      "timing": 4.2
    },
    {
      "youtube_link": "https://www.youtube.com/watch?v=wacmaxGoaO0",
      "timing": 2.98
    }
  ],
  "staff_2.png": [
    {
      "youtube_link": "https://www.youtube.com/watch?v=-QxRTIQ1sR8",
      "timing": 3.6047
    },
    {
      "youtube_link": "https://www.youtube.com/watch?v=5ZxEn-dsvw8",
      "timing": 6.8
    },
    {
      "youtube_link": "https://www.youtube.com/watch?v=aBfdruMBBz8",
      "timing": 7.88
    },
    {
      "youtube_link": "https://www.youtube.com/watch?v=MWTW7Jj1RcU",
      "timing": 8.66
    },
    {
      "youtube_link": "https://www.youtube.com/watch?v=MZ-53dpPPr0",
      "timing": 9.2017
    },
    {
      "youtube_link": "https://www.youtube.com/watch?v=OfrxgQQqaA8",
      "timing": 9.4
    },
    {
      "youtube_link": "https://www.youtube.com/watch?v=R5EoRegSyDw",
      "timing": 9.8
    },
    {
      "youtube_link": "https://www.youtube.com/watch?v=rLvve9ks3Xs",
      "timing": 7.82
    },
    {
      "youtube_link": "https://www.youtube.com/watch?v=sfkXHfz6AtE",
      "timing": 8.8257
    },
    {
      "youtube_link": "https://www.youtube.com/watch?v=wacmaxGoaO0",
      "timing": 7.9
    }
  ],
  "staff_3.png": [
    {
      "youtube_link": "https://www.youtube.com/watch?v=-QxRTIQ1sR8",
      "timing": 4.5243
    },
    {
      "youtube_link": "https://www.youtube.com/watch?v=5ZxEn-dsvw8",
      "timing": 11.5
    },
    {
      "youtube_link": "https://www.youtube.com/watch?v=aBfdruMBBz8",
      "timing": 11.56
    },
    {
      "youtube_link": "https://www.youtube.com/watch?v=MWTW7Jj1RcU",
      "timing": 12.68
    },
    {
      "youtube_link": "https://www.youtube.com/watch?v=MZ-53dpPPr0",
      "timing": 11.78
    },
    {
      "youtube_link": "https://www.youtube.com/watch?v=OfrxgQQqaA8",
      "timing": 13.42
    },
    {
      "youtube_link": "https://www.youtube.com/watch?v=R5EoRegSyDw",
      "timing": 13.9473
    },
    {
      "youtube_link": "https://www.youtube.com/watch?v=rLvve9ks3Xs",
      "timing": 11.48
    },
    {
      "youtube_link": "https://www.youtube.com/watch?v=sfkXHfz6AtE",
      "timing": 11.96
    },
    {
      "youtube_link": "https://www.youtube.com/watch?v=wacmaxGoaO0",
      "timing": 11.86
    }
  ],
  "staff_4.png": [
    {
      "youtube_link": "https://www.youtube.com/watch?v=-QxRTIQ1sR8",
      "timing": 6.0055
    },
    {
      "youtube_link": "https://www.youtube.com/watch?v=5ZxEn-dsvw8",
      "timing": 15.94
    },
    {
      "youtube_link": "https://www.youtube.com/watch?v=aBfdruMBBz8",
      "timing": 15.02
    },
    {
      "youtube_link": "https://www.youtube.com/watch?v=MWTW7Jj1RcU",
      "timing": 16.62
    },
    {
      "youtube_link": "https://www.youtube.com/watch?v=MZ-53dpPPr0",
      "timing": 12.98
    },
    {
      "youtube_link": "https://www.youtube.com/watch?v=OfrxgQQqaA8",
      "timing": 17.54
    },
    {
      "youtube_link": "https://www.youtube.com/watch?v=R5EoRegSyDw",
      "timing": 16.9
    },
    {
      "youtube_link": "https://www.youtube.com/watch?v=rLvve9ks3Xs",
      "timing": 15.46
    },
    {
      "youtube_link": "https://www.youtube.com/watch?v=sfkXHfz6AtE",
      "timing": 15.62
    },
    {
      "youtube_link": "https://www.youtube.com/watch?v=wacmaxGoaO0",
      "timing": 15.96
    }
  ],
  "staff_5.png": [
    {
      "youtube_link": "https://www.youtube.com/watch?v=-QxRTIQ1sR8",
      "timing": 6.4364
    },
    {
      "youtube_link": "https://www.youtube.com/watch?v=5ZxEn-dsvw8",
      "timing": 20.5
    },
    {
      "youtube_link": "https://www.youtube.com/watch?v=aBfdruMBBz8",
      "timing": 18.5567
    },
    {
      "youtube_link": "https://www.youtube.com/watch?v=MWTW7Jj1RcU",
      "timing": 20.7822
    },
    {
      "youtube_link": "https://www.youtube.com/watch?v=MZ-53dpPPr0",
      "timing": 16.7248
    },
    {
      "youtube_link": "https://www.youtube.com/watch?v=OfrxgQQqaA8",
      "timing": 21.44
    },
    {
      "youtube_link": "https://www.youtube.com/watch?v=R5EoRegSyDw",
      "timing": 20.1
    },
    {
      "youtube_link": "https://www.youtube.com/watch?v=rLvve9ks3Xs",
      "timing": 19.6
    },
    {
      "youtube_link": "https://www.youtube.com/watch?v=sfkXHfz6AtE",
      "timing": 19.1744
    },
    {
      "youtube_link": "https://www.youtube.com/watch?v=wacmaxGoaO0",
      "timing": 19.7
    }
  ],
  "staff_6.png": [
    {
      "youtube_link": "https://www.youtube.com/watch?v=-QxRTIQ1sR8",
      "timing": 6.9874
    },
    {
      "youtube_link": "https://www.youtube.com/watch?v=5ZxEn-dsvw8",
      "timing": 22.91
    },
    {
      "youtube_link": "https://www.youtube.com/watch?v=aBfdruMBBz8",
      "timing": 21.6
    },
    {
      "youtube_link": "https://www.youtube.com/watch?v=MWTW7Jj1RcU",
      "timing": 24.06
    },
    {
      "youtube_link": "https://www.youtube.com/watch?v=MZ-53dpPPr0",
      "timing": 17.9123
    },
    {
      "youtube_link": "https://www.youtube.com/watch?v=OfrxgQQqaA8",
      "timing": 24.64
    },
    {
      "youtube_link": "https://www.youtube.com/watch?v=R5EoRegSyDw",
      "timing": 22.2664
    },
    {
      "youtube_link": "https://www.youtube.com/watch?v=rLvve9ks3Xs",
      "timing": 22.614
    },
    {
      "youtube_link": "https://www.youtube.com/watch?v=sfkXHfz6AtE",
      "timing": 21.98
    },
    {
      "youtube_link": "https://www.youtube.com/watch?v=wacmaxGoaO0",
      "timing": 22.96
    }
  ],
  "staff_7.png": [
    {
      "youtube_link": "https://www.youtube.com/watch?v=-QxRTIQ1sR8",
      "timing": 11.2
    },
    {
      "youtube_link": "https://www.youtube.com/watch?v=5ZxEn-dsvw8",
      "timing": 24.3637
    },
    {
      "youtube_link": "https://www.youtube.com/watch?v=aBfdruMBBz8",
      "timing": 25.12
    },
    {
      "youtube_link": "https://www.youtube.com/watch?v=MWTW7Jj1RcU",
      "timing": 29.24
    },
    {
      "youtube_link": "https://www.youtube.com/watch?v=MZ-53dpPPr0",
      "timing": 18.1686
    },
    {
      "youtube_link": "https://www.youtube.com/watch?v=OfrxgQQqaA8",
      "timing": 28.76
    },
    {
      "youtube_link": "https://www.youtube.com/watch?v=R5EoRegSyDw",
      "timing": 23.92
    },
    {
      "youtube_link": "https://www.youtube.com/watch?v=rLvve9ks3Xs",
      "timing": 27.16
    },
    {
      "youtube_link": "https://www.youtube.com/watch?v=sfkXHfz6AtE",
      "timing": 25.64
    },
    {
      "youtube_link": "https://www.youtube.com/watch?v=wacmaxGoaO0",
      "timing": 28.42
    }
  ],
  "staff_8.png": [
    {
      "youtube_link": "https://www.youtube.com/watch?v=-QxRTIQ1sR8",
      "timing": 16.26
    },
    {
      "youtube_link": "https://www.youtube.com/watch?v=5ZxEn-dsvw8",
      "timing": 26.5971
    },
    {
      "youtube_link": "https://www.youtube.com/watch?v=aBfdruMBBz8",
      "timing": 28.64
    },
    {
      "youtube_link": "https://www.youtube.com/watch?v=MWTW7Jj1RcU",
      "timing": 33.0867
    },
    {
      "youtube_link": "https://www.youtube.com/watch?v=MZ-53dpPPr0",
      "timing": 19.4431
    },
    {
      "youtube_link": "https://www.youtube.com/watch?v=OfrxgQQqaA8",
      "timing": 32.6
    },
    {
      "youtube_link": "https://www.youtube.com/watch?v=R5EoRegSyDw",
      "timing": 25.88
    },
    {
      "youtube_link": "https://www.youtube.com/watch?v=rLvve9ks3Xs",
      "timing": 30.5
    },
    {
      "youtube_link": "https://www.youtube.com/watch?v=sfkXHfz6AtE",
      "timing": 28.628
    },
    {
      "youtube_link": "https://www.youtube.com/watch?v=wacmaxGoaO0",
      "timing": 32.2
    }
  ],
  "staff_9.png": [
    {
      "youtube_link": "https://www.youtube.com/watch?v=-QxRTIQ1sR8",
      "timing": 21.4
    },
    {
      "youtube_link": "https://www.youtube.com/watch?v=5ZxEn-dsvw8",
      "timing": 31.34
    },
    {
      "youtube_link": "https://www.youtube.com/watch?v=aBfdruMBBz8",
      "timing": 32.0
    },
    {
      "youtube_link": "https://www.youtube.com/watch?v=MWTW7Jj1RcU",
      "timing": 37.24
    },
    {
      "youtube_link": "https://www.youtube.com/watch?v=MZ-53dpPPr0",
      "timing": 22.24
    },
    {
      "youtube_link": "https://www.youtube.com/watch?v=OfrxgQQqaA8",
      "timing": 36.4
    },
    {
      "youtube_link": "https://www.youtube.com/watch?v=R5EoRegSyDw",
      "timing": 29.64
    },
    {
      "youtube_link": "https://www.youtube.com/watch?v=rLvve9ks3Xs",
      "timing": 35.4
    },
    {
      "youtube_link": "https://www.youtube.com/watch?v=sfkXHfz6AtE",
      "timing": 31.98
    },
    {
      "youtube_link": "https://www.youtube.com/watch?v=wacmaxGoaO0",
      "timing": 36.4164
    }
  ]
}